predicate/__init__.py
predicate/combinator.py
predicate/comparator.py
predicate/main.py
predicate/predicates.py
predicate/utils.py
predicate-0.2.0.dist-info/LICENSE
predicate-0.2.0.dist-info/METADATA
predicate-0.2.0.dist-info/WHEEL
predicate-0.2.0.dist-info/top_level.txt
predicate-0.2.0.dist-info/RECORD
